cl/runtime/__init__.py
cl/runtime/decorators/__init__.py
cl/runtime/primitive/__init__.py
cl/runtime/primitive/string_util.py
cl/runtime/schema/__init__.py
cl/runtime/schema/decl/__init__.py
cl/runtime/schema/decl/atomic_type.py
cl/runtime/schema/decl/element_modification_type.py
cl/runtime/schema/decl/enum_decl.py
cl/runtime/schema/decl/enum_decl_key.py
cl/runtime/schema/decl/enum_item_decl.py
cl/runtime/schema/decl/handler_declare_block_decl.py
cl/runtime/schema/decl/handler_declare_decl.py
cl/runtime/schema/decl/handler_implement_block_decl.py
cl/runtime/schema/decl/handler_implement_decl.py
cl/runtime/schema/decl/handler_param_decl.py
cl/runtime/schema/decl/handler_type.py
cl/runtime/schema/decl/handler_variable_decl.py
cl/runtime/schema/decl/index_decl.py
cl/runtime/schema/decl/index_sort_order_enum.py
cl/runtime/schema/decl/interface_decl.py
cl/runtime/schema/decl/interface_decl_key.py
cl/runtime/schema/decl/interface_implement_decl.py
cl/runtime/schema/decl/language.py
cl/runtime/schema/decl/language_key.py
cl/runtime/schema/decl/module.py
cl/runtime/schema/decl/module_key.py
cl/runtime/schema/decl/package.py
cl/runtime/schema/decl/package_dependency.py
cl/runtime/schema/decl/package_key.py
cl/runtime/schema/decl/type_argument_decl.py
cl/runtime/schema/decl/type_decl.py
cl/runtime/schema/decl/type_decl_key.py
cl/runtime/schema/decl/type_element_decl.py
cl/runtime/schema/decl/type_index_decl.py
cl/runtime/schema/decl/type_kind.py
cl/runtime/schema/decl/type_member_decl.py
cl/runtime/schema/decl/type_param_constraint_type.py
cl/runtime/schema/decl/type_param_decl.py
cl/runtime/schema/decl/value_decl.py
cl/runtime/schema/type/__init__.py
cl/runtime/schema/type/data_decl.py
cl/runtime/schema/type/enum_decl.py
cl/runtime/schema/type/field_decl.py
cl/runtime/schema/type/package_decl.py
cl/runtime/schema/type/package_decl_key.py
cl/runtime/schema/type/primitive_decl.py
cl/runtime/schema/type/type_decl.py
cl/runtime/schema/type/type_decl_key.py
cl_runtime-2.0.4.dist-info/LICENSE
cl_runtime-2.0.4.dist-info/METADATA
cl_runtime-2.0.4.dist-info/WHEEL
cl_runtime-2.0.4.dist-info/top_level.txt
cl_runtime-2.0.4.dist-info/RECORD
