Metadata-Version: 2.1
Name: cl-runtime
Version: 2.0.4
Summary: CompatibL Runtime Community Edition
Home-page: https://github.com/compatibl/runtime
Author: The Project Contributors
License: Apache Software License
Project-URL: Source Code, https://github.com/compatibl/runtime
Classifier: Development Status :: 3 - Alpha
Classifier: Intended Audience :: Developers
Classifier: Topic :: Software Development
Classifier: Topic :: Scientific/Engineering
Classifier: License :: OSI Approved :: Apache Software License
Classifier: Programming Language :: Python :: 3.10
Classifier: Programming Language :: Python :: 3.11
Classifier: Programming Language :: Python :: 3.12
Classifier: Operating System :: OS Independent
License-File: LICENSE
Requires-Dist: PyJWT >=2.4.0
Requires-Dist: SQLAlchemy >=1.4.40
Requires-Dist: aiofiles >=0.8.0
Requires-Dist: aiomysql >=0.1.1
Requires-Dist: alembic >=1.8.1
Requires-Dist: asyncio >=3.4.0
Requires-Dist: celery >=5.2.7
Requires-Dist: click >=8.1.3
Requires-Dist: concurrent-log-handler >=0.9.20
Requires-Dist: dynaconf >=3.1.7
Requires-Dist: fastapi-event >=0.1.3
Requires-Dist: fastapi >=0.85.0
Requires-Dist: greenlet >=1.1.3
Requires-Dist: gunicorn >=20.1.0
Requires-Dist: httpx >=0.23.3
Requires-Dist: jinja2 >=3.0.3
Requires-Dist: kaleido >=0.2.1
Requires-Dist: markdown2 >=2.4.2
Requires-Dist: memoization >=0.4.0
Requires-Dist: mmh3 >=3.0.0
Requires-Dist: numpy >=1.24.2
Requires-Dist: orjson >=3.8.6
Requires-Dist: pandas >=1.5.3
Requires-Dist: pdoc >=12.0.2
Requires-Dist: plotly >=5.5.0
Requires-Dist: pymongo >=4.0.1
Requires-Dist: pytest >=6.1.1
Requires-Dist: python-dateutil >=2.8.2
Requires-Dist: python-dotenv >=0.19.2
Requires-Dist: pythondi >=1.2.4
Requires-Dist: redis >=4.3.4
Requires-Dist: reportlab >=3.6.5
Requires-Dist: requests >=2.28.1
Requires-Dist: sse-starlette >=1.2.1
Requires-Dist: typing-inspect >=0.7.1
Requires-Dist: ujson >=5.4.0
Requires-Dist: uvicorn >=0.18.3
Requires-Dist: websockets >=10.4
Requires-Dist: xmltodict >=0.12.0
